Tool.py
gyte/__init__.py
gyte/gyteone.py
gyte-1.0.1.dist-info/LICENSE.txt
gyte-1.0.1.dist-info/METADATA
gyte-1.0.1.dist-info/WHEEL
gyte-1.0.1.dist-info/top_level.txt
gyte-1.0.1.dist-info/RECORD
