Metadata-Version: 2.1
Name: gyte
Version: 1.0.1
Summary: This is a test library！
Home-page: https://github.com/
Author: GuoYi
Author-email: UNKNOWN
License: UNKNOWN
Platform: UNKNOWN
